django_allauth_skins/__init__.py
django_allauth_skins/apps.py
django_allauth_skins/models.py
django_allauth_skins/static/allauth_skins/css/.gitkeep
django_allauth_skins/static/allauth_skins/images/.gitkeep
django_allauth_skins/static/allauth_skins/js/.gitkeep
django_allauth_skins/templates/allauth_skins/.gitkeep
django_allauth_skins/urls.py
django_allauth_skins-0.1.0.dist-info/LICENSE
django_allauth_skins-0.1.0.dist-info/WHEEL
django_allauth_skins-0.1.0.dist-info/METADATA
django_allauth_skins-0.1.0.dist-info/RECORD
